Workbook

Sheet Dashboard
A1: AML ANALYST + ANALYTICS | 8-WEEK PLANNER DASHBOARD
A3: Programme Status | B3: Proposed | D3: Week | E3: Theme | F3: Tasks | G3: Complete | H3: Week %
A4: Start Date | D4: 1 | E4: AML Foundations + Ireland/EU | F4: =COUNTIF('8-Week Planner'!$A$5:$A$37,D4) -> 4 | G4: =COUNTIFS('8-Week Planner'!$A$5:$A$37,D4,'8-Week Planner'!$L$5:$L$37,"Complete") -> 0 | H4: =IF(F4=0,0,G4/F4) -> 0
A5: Overall Completion | B5: =IF(B7=0,0,B6/B7) -> 0 | D5: 2 | E5: KYC / CDD / EDD + Screening | F5: =COUNTIF('8-Week Planner'!$A$5:$A$37,D5) -> 3 | G5: =COUNTIFS('8-Week Planner'!$A$5:$A$37,D5,'8-Week Planner'!$L$5:$L$37,"Complete") -> 0 | H5: =IF(F5=0,0,G5/F5) -> 0
A6: Tasks Complete | B6: =COUNTIF('8-Week Planner'!$L$5:$L$37,"Complete") -> 0 | D6: 3 | E6: Transaction Monitoring + Core Typologies | F6: =COUNTIF('8-Week Planner'!$A$5:$A$37,D6) -> 4 | G6: =COUNTIFS('8-Week Planner'!$A$5:$A$37,D6,'8-Week Planner'!$L$5:$L$37,"Complete") -> 0 | H6: =IF(F6=0,0,G6/F6) -> 0
A7: Total Tasks | B7: =COUNTA('8-Week Planner'!$C$5:$C$37) -> 33 | D7: 4 | E7: Advanced Typologies + Python | F7: =COUNTIF('8-Week Planner'!$A$5:$A$37,D7) -> 4 | G7: =COUNTIFS('8-Week Planner'!$A$5:$A$37,D7,'8-Week Planner'!$L$5:$L$37,"Complete") -> 0 | H7: =IF(F7=0,0,G7/F7) -> 0
D8: 5 | E8: Investigations + Case Narratives | F8: =COUNTIF('8-Week Planner'!$A$5:$A$37,D8) -> 4 | G8: =COUNTIFS('8-Week Planner'!$A$5:$A$37,D8,'8-Week Planner'!$L$5:$L$37,"Complete") -> 0 | H8: =IF(F8=0,0,G8/F8) -> 0
A9: Quick Inputs | B9: Tailor these to your setup | D9: 6 | E9: Network & Entity Analytics | F9: =COUNTIF('8-Week Planner'!$A$5:$A$37,D9) -> 4 | G9: =COUNTIFS('8-Week Planner'!$A$5:$A$37,D9,'8-Week Planner'!$L$5:$L$37,"Complete") -> 0 | H9: =IF(F9=0,0,G9/F9) -> 0
A10: Weekly Study Hours | D10: 7 | E10: Detection Analytics, ML Evaluation & Model Validation | F10: =COUNTIF('8-Week Planner'!$A$5:$A$37,D10) -> 5 | G10: =COUNTIFS('8-Week Planner'!$A$5:$A$37,D10,'8-Week Planner'!$L$5:$L$37,"Complete") -> 0 | H10: =IF(F10=0,0,G10/F10) -> 0
A11: Primary SQL Tool | B11: PostgreSQL / DuckDB | D11: 8 | E11: Ireland Workflow, Capstone & Positioning | F11: =COUNTIF('8-Week Planner'!$A$5:$A$37,D11) -> 5 | G11: =COUNTIFS('8-Week Planner'!$A$5:$A$37,D11,'8-Week Planner'!$L$5:$L$37,"Complete") -> 0 | H11: =IF(F11=0,0,G11/F11) -> 0
A12: Primary Python Tool | B12: Jupyter / VS Code
A13: BI Tool | B13: Power BI
A14: Portfolio | B14: Git / GitHub
A16: Locked outcome: practical AML readiness + demonstrable SQL, Python and graph evidence, not theory-only study.

Sheet 8-Week Planner
A1: 8-WEEK AML ANALYST + CODING INTERACTIVE PLANNER
A2: Programme remains PROPOSED until you set the status on the Dashboard. All six scope areas are locked. Rows shaded orange are additions on top of the base plan.
A4: Week | B4: Theme | C4: Task / Topic | D4: What You Learn | E4: AML / Investigation Focus | F4: Coding / Technical Focus | G4: Practical Exercise | H4: Tool(s) | I4: Complementary Content | J4: Evidence / Deliverable | K4: Priority | L4: Status | M4: Confidence (1-5) | N4: Planned Hrs | O4: Actual Hrs | P4: Start Date | Q4: Due Date | R4: % Complete | S4: Notes
A5: 1 | B5: AML Foundations + Ireland/EU | C5: AML lifecycle & risk-based approach | D5: Placement, layering, integration; why risk-based monitoring exists | E5: Recognise the laundering lifecycle and core red flags | F5: SQL refresh: SELECT, WHERE, GROUP BY, HAVING | G5: Profile a synthetic transaction table and isolate unusual transaction groups | H5: PostgreSQL/DuckDB; VS Code/Jupyter | I5: Short Ireland/EU AML orientation + worked examples | J5: SQL notebook: baseline transaction profiling | K5: High | L5: Not Started | P5: =IF(Dashboard!$B$4="","",Dashboard!$B$4+(A5-1)*7) | Q5: =IF(P5="","",P5+6) | R5: =IF(L5="Complete",1,IF(L5="Review",0.75,IF(L5="In Progress",0.5,IF(L5="Blocked",0.25,0)))) -> 0
A6: 1 | B6: AML Foundations + Ireland/EU | C6: Structuring & threshold behaviour | D6: How structuring/smurfing avoids controls and how patterns emerge over time | E6: Repeated values below thresholds; multiple transactions; time clustering | F6: Date functions, aggregations, HAVING, basic rolling logic | G6: Detect repeated sub-threshold activity across customer/date windows | H6: SQL | I6: Typology walkthrough: structuring examples | J6: Detection query + explanation of false positives | K6: High | L6: Not Started | P6: =IF(Dashboard!$B$4="","",Dashboard!$B$4+(A6-1)*7) | Q6: =IF(P6="","",P6+6) | R6: =IF(L6="Complete",1,IF(L6="Review",0.75,IF(L6="In Progress",0.5,IF(L6="Blocked",0.25,0)))) -> 0
A7: 1 | B7: AML Foundations + Ireland/EU | C7: Mule account activity | D7: Mule behaviour, pass-through activity and rapid onward movement | E7: Incoming funds followed by rapid dispersal | F7: Joins + time-difference logic | G7: Identify candidate mule accounts in a synthetic payments dataset | H7: SQL | I7: Mule-account case examples | J7: Mule detection query + short analyst note | K7: High | L7: Not Started | P7: =IF(Dashboard!$B$4="","",Dashboard!$B$4+(A7-1)*7) | Q7: =IF(P7="","",P7+6) | R7: =IF(L7="Complete",1,IF(L7="Review",0.75,IF(L7="In Progress",0.5,IF(L7="Blocked",0.25,0)))) -> 0
A8: 1 | B8: AML Foundations + Ireland/EU | C8: Irish/EU AML operating model | D8: Irish obligations, CBI context, FIU Ireland, Revenue, STR concept, AMLA overview | E8: Understand where an analyst sits in the reporting chain | F8: No heavy coding; map fields/evidence needed for reporting | G8: Draw the alert to investigation to escalation to STR workflow | H8: Excel/PowerPoint optional | I8: Ireland-first regulator/FIU material | J8: 1-page Irish AML workflow map | K8: Medium | L8: Not Started | P8: =IF(Dashboard!$B$4="","",Dashboard!$B$4+(A8-1)*7) | Q8: =IF(P8="","",P8+6) | R8: =IF(L8="Complete",1,IF(L8="Review",0.75,IF(L8="In Progress",0.5,IF(L8="Blocked",0.25,0)))) -> 0
A9: 2 | B9: KYC / CDD / EDD + Screening | C9: KYC & customer risk profile | D9: Identity, ownership, expected activity, risk factors and customer segmentation | E9: Compare actual behaviour with expected profile | F9: SQL JOINs; CASE; CTEs | G9: Join customer/KYC data to transaction behaviour and flag profile mismatches | H9: SQL | I9: CDD/EDD worked examples | J9: Customer-risk query + exception list | K9: High | L9: Not Started | P9: =IF(Dashboard!$B$4="","",Dashboard!$B$4+(A9-1)*7) | Q9: =IF(P9="","",P9+6) | R9: =IF(L9="Complete",1,IF(L9="Review",0.75,IF(L9="In Progress",0.5,IF(L9="Blocked",0.25,0)))) -> 0
A10: 2 | B10: KYC / CDD / EDD + Screening | C10: CDD vs EDD & risk scoring | D10: When enhanced review is warranted; source of funds/wealth; ownership | E10: Escalation triggers and evidence gaps | F10: CTEs + reusable risk flags | G10: Build a risk scoring query using customer + transaction indicators | H10: SQL | I10: EDD case narrative example | J10: CDD/EDD decision matrix | K10: High | L10: Not Started | P10: =IF(Dashboard!$B$4="","",Dashboard!$B$4+(A10-1)*7) | Q10: =IF(P10="","",P10+6) | R10: =IF(L10="Complete",1,IF(L10="Review",0.75,IF(L10="In Progress",0.5,IF(L10="Blocked",0.25,0)))) -> 0
A11: 2 | B11: KYC / CDD / EDD + Screening | C11: Sanctions / PEP screening | D11: PEP, sanctions, screening alerts, false matches, adverse context | E11: Screening alert review and disposition | F11: String cleaning + fuzzy matching concept | G11: Create mock names and test exact/near-match screening logic | H11: SQL/Python; rapidfuzz | I11: EU/Ireland sanctions/PEP screening material | J11: Screening result table + analyst rationale | K11: High | L11: Not Started | P11: =IF(Dashboard!$B$4="","",Dashboard!$B$4+(A11-1)*7) | Q11: =IF(P11="","",P11+6) | R11: =IF(L11="Complete",1,IF(L11="Review",0.75,IF(L11="In Progress",0.5,IF(L11="Blocked",0.25,0)))) -> 0
A12: 3 | B12: Transaction Monitoring + Core Typologies | C12: Transaction monitoring architecture | D12: Ingestion -> scenario/rule -> threshold -> alert -> case -> disposition -> tuning | E12: How alerts are generated and prioritised | F12: SQL scenario query design | G12: Implement 2-3 monitoring scenarios against synthetic data | H12: SQL; GitHub | I12: TM system workflow explainer | J12: Mini transaction-monitoring rules repo | K12: High | L12: Not Started | P12: =IF(Dashboard!$B$4="","",Dashboard!$B$4+(A12-1)*7) | Q12: =IF(P12="","",P12+6) | R12: =IF(L12="Complete",1,IF(L12="Review",0.75,IF(L12="In Progress",0.5,IF(L12="Blocked",0.25,0)))) -> 0
A13: 3 | B13: Transaction Monitoring + Core Typologies | C13: Layering & rapid movement | D13: Multi-step fund movement designed to obscure origin | E13: Rapid movement, multiple hops, unusual destinations | F13: Window functions; LAG/LEAD; time intervals | G13: Detect quick in-and-out movement and multi-hop patterns | H13: SQL | I13: Layering case walkthrough | J13: Layering detection queries | K13: High | L13: Not Started | P13: =IF(Dashboard!$B$4="","",Dashboard!$B$4+(A13-1)*7) | Q13: =IF(P13="","",P13+6) | R13: =IF(L13="Complete",1,IF(L13="Review",0.75,IF(L13="In Progress",0.5,IF(L13="Blocked",0.25,0)))) -> 0
A14: 3 | B14: Transaction Monitoring + Core Typologies | C14: Funnel accounts & velocity | D14: Many distributed deposits converging on an account; high activity bursts | E14: Geographic/transaction concentration and velocity | F14: PARTITION BY; rolling COUNT/SUM; velocity checks | G14: Build rolling 1h/24h activity metrics and flag funnel-like behaviour | H14: SQL | I14: Funnel-account examples | J14: Velocity query + alert explanation | K14: High | L14: Not Started | P14: =IF(Dashboard!$B$4="","",Dashboard!$B$4+(A14-1)*7) | Q14: =IF(P14="","",P14+6) | R14: =IF(L14="Complete",1,IF(L14="Review",0.75,IF(L14="In Progress",0.5,IF(L14="Blocked",0.25,0)))) -> 0
A15: 3 | B15: Transaction Monitoring + Core Typologies | C15: False positives & threshold logic | D15: Why rules over-alert and how analysts judge quality | E15: Alert quality, customer context, false-positive drivers | F15: Threshold parameterisation in SQL | G15: Vary thresholds and measure alert counts | H15: SQL | I15: Scenario-tuning explainer | J15: Threshold comparison table | K15: High | L15: Not Started | P15: =IF(Dashboard!$B$4="","",Dashboard!$B$4+(A15-1)*7) | Q15: =IF(P15="","",P15+6) | R15: =IF(L15="Complete",1,IF(L15="Review",0.75,IF(L15="In Progress",0.5,IF(L15="Blocked",0.25,0)))) -> 0
A16: 4 | B16: Advanced Typologies + Python | C16: Trade-Based Money Laundering (TBML) | D16: Trade/payment anomalies; invoice/value inconsistencies; counterparties | E16: Mismatch and unusual trade relationships | F16: SQL reconciliation / outlier checks | G16: Flag synthetic trade-payment mismatches and unusual counterparties | H16: SQL | I16: TBML practical explainer | J16: TBML exceptions report | K16: Medium | L16: Not Started | P16: =IF(Dashboard!$B$4="","",Dashboard!$B$4+(A16-1)*7) | Q16: =IF(P16="","",P16+6) | R16: =IF(L16="Complete",1,IF(L16="Review",0.75,IF(L16="In Progress",0.5,IF(L16="Blocked",0.25,0)))) -> 0
... A37: 8 | B37: Ireland Workflow, Capstone & Positioning | C37: Positioning & job conversion | D37: Convert the portfolio into applications | E37: Frame yourself as a Financial Crime / AML detection analyst | F37: Tailor CV and LinkedIn to the evidence; map roles | G37: Rewrite CV/LinkedIn, build a Dublin target-role list, start applying | H37: LinkedIn; job boards | I37: ACAMS / Compliance Institute (ACOI) optional | J37: Revised CV, target-role list, applications out | K37: High | L37: Not Started | P37: =IF(Dashboard!$B$4="","",Dashboard!$B$4+(A37-1)*7) | Q37: =IF(P37="","",P37+6) | R37: =IF(L37="Complete",1,IF(L37="Review",0.75,IF(L37="In Progress",0.5,IF(L37="Blocked",0.25,0)))) -> 0

Sheet Locked Scope
A1: LOCKED AML ANALYST + ANALYTICS PROGRAMME SCOPE
A3: ID | B3: Mandatory Area | C3: Locked Coverage | D3: Coding / Technical Link | E3: Programme Status | F3: Notes
A4: 1 | B4: AML fundamentals and typologies | C4: Structuring; layering; mule account activity; funnel accounts; circular transactions; shell company activity; TBML; wallet/crypto layering | D4: SQL pattern detection; rolling windows; linked-account logic; Python and graph (NetworkX) analysis | E4: LOCKED | F4: Cannot be removed unless explicitly reopened. Network typologies now built out in Week 6.
A5: 2 | B5: Transaction monitoring and investigations | C5: Alert triage; customer-profile comparison; source/destination of funds; false positives; escalation; case narratives | D5: SQL alert queries; Python investigation timelines; threshold testing | E5: LOCKED | F5: Must include end-to-end investigation practice.
A6: 3 | B6: KYC / CDD / EDD + sanctions / PEP screening | C6: Customer risk; beneficial ownership; source of funds/wealth; sanctions/PEP alerts; screening logic | D6: SQL customer-to-transaction joins; fuzzy matching concepts | E6: LOCKED | F6: Must be practical, not definition-only.
A7: 4 | B7: Irish / EU AML workflow | C7: Irish AML obligations; FIU Ireland; STRs; goAML; Revenue reporting context; EU AML framework / AMLA | D7: Evidence capture; case documentation; workflow traceability | E7: LOCKED | F7: Ireland-first; EU where directly relevant.
A8: 5 | B8: SQL for AML analytics | C8: Joins; CTEs; window functions; rolling transaction totals; pattern detection; velocity checks; linked accounts | D8: PostgreSQL or DuckDB; repeatable detection queries | E8: LOCKED | F8: Must produce portfolio-ready SQL evidence.
A9: 6 | B9: Python / data analytics | C9: pandas; transaction aggregation; anomaly detection; threshold tuning; false-positive analysis; ML evaluation and model validation | D9: Python; pandas; NumPy; scikit-learn; Jupyter / VS Code | E9: LOCKED | F9: ML applied to AML, not generic ML engineering. Model-validation content elevated in Week 7.

Sheet Capstone
A1: WEEK 8 CAPSTONE, END-TO-END AML ANALYTICS CASE
A3: Step | B3: Capstone Stage | C3: What You Must Do | D3: SQL Evidence | E3: Python Evidence | F3: AML Decision Evidence | G3: Status | H3: Notes
A4: 1 | B4: Profile the customer | C4: Review KYC/customer attributes and expected activity | D4: Customer/KYC query | E4: Customer profile dataframe | F4: Risk profile summary | G4: Not Started
A5: 2 | B5: Query transactions | C5: Establish behavioural baseline and timeline | D5: Transaction baseline queries | E5: Transaction aggregation | F5: Baseline observations | G5: Not Started
A6: 3 | B6: Detect suspicious patterns | C6: Run typology detections including graph checks | D6: Structuring/layering/mule queries | E6: Detection functions + NetworkX ring check | F6: Triggered typologies | G6: Not Started
A7: 4 | B7: Generate alerts | C7: Apply thresholds and risk scoring | D7: Scenario output tables | E7: Alert scoring code | F7: Alert rationale | G7: Not Started
A8: 5 | B8: Triage alerts | C8: Rank and prioritise alerts | D8: Alert severity query | E8: Alert triage dataframe | F8: Triage decision | G8: Not Started
A9: 6 | B9: Investigate | C9: Gather customer/transaction/counterparty evidence | D9: Evidence extraction | E9: Timeline/flow analysis | F9: Investigation notes | G9: Not Started
A10: 7 | B10: Test false positive | C10: Challenge the alert against context | D10: Comparison queries | E10: Threshold sensitivity | F10: FP/TP conclusion | G10: Not Started
A11: 8 | B11: Explain evidence | C11: Create a concise evidence chain | D11: Reproducible query pack | E11: Reproducible notebook | F11: Evidence summary | G11: Not Started
A12: 9 | B12: Escalate appropriately | C12: Decide whether escalation is warranted | D12: Supporting extracts | E12: Supporting analysis | F12: Escalation rationale | G12: Not Started
A13: 10 | B13: Draft STR-style narrative | C13: Prepare an Ireland-appropriate narrative structure | D13: Evidence references | E13: Summary tables | F13: Case narrative | G13: Not Started
A14: 11 | B14: Evaluate detection performance | C14: Assess rules/model quality | D14: Alert metrics | E14: Precision/recall/FP analysis | F14: Control effectiveness summary | G14: Not Started

Sheet Resources
A1: COMPLEMENTARY CONTENT & TOOLS, IRELAND / EU FIRST
A3: Type | B3: Topic | C3: Resource / Tool | D3: Jurisdiction | E3: How It Supports Training | F3: URL / Reference | G3: Use
A4: Video | B4: STR / goAML practical workflow | C4: Law Society of Ireland + FIU Ireland + Revenue webinar | D4: Ireland | E4: Practical STR reporting workflow and goAML context | F4: https://lawschooleduit.cloud.panopto.eu/Panopto/Pages/Viewer.aspx?id=d7e51539-f581-46c1-8651-b4030114e07b | G4: Week 8
A5: Official | B5: AML/CFT supervision | C5: Central Bank of Ireland AML/CFT | D5: Ireland | E5: Irish regulatory context and sector guidance | F5: https://www.centralbank.ie/regulation/anti-money-laundering-and-countering-the-financing-of-terrorism | G5: Wk 1, 2, 8
A6: Official | B6: EU AML framework / AMLA | C6: AMLA official site | D6: EU | E6: The new EU framework and single rulebook | F6: https://www.amla.europa.eu/ | G6: Wk 1 / ref
A7: Official | B7: Suspicious transaction reporting | C7: FIU Ireland / Garda Economic Crime Bureau | D7: Ireland | E7: Reporting and financial intelligence context | F7: https://www.garda.ie/en/about-us/organised-serious-crime/garda-national-economic-crime-bureau/ | G7: Week 8
A8: Dataset | B8: Synthetic payments | C8: PaySim synthetic transaction dataset | D8: Global / tool | E8: Safe practice data for structuring, mule, layering and threshold work | F8: https://www.kaggle.com/datasets/ealaxi/paysim1 | G8: Wk 1-7
A9: Dataset | B9: Sanctions / PEP data | C9: OpenSanctions | D9: Global / tool | E9: Real sanctions and PEP data for the screening module | F9: https://www.opensanctions.org/ | G9: Week 2
A10: Tool | B10: SQL engine | C10: PostgreSQL or DuckDB | D10: Tool | E10: Joins, CTEs, windows, rolling sums, velocity, linked-account analysis | F10: https://www.postgresql.org/ | G10: Wk 1-8
A11: Tool | B11: Python analytics | C11: Python + pandas | D11: Tool | E11: Aggregation, investigation, threshold tuning and anomaly detection | F11: https://pandas.pydata.org/ | G11: Wk 4-8
A12: Tool | B12: Graph analytics | C12: NetworkX + pyvis | D12: Tool | E12: Transaction networks, circular-flow and ring detection, visualisation | F12: https://networkx.org/ | G12: Week 6
A13: Tool | B13: ML evaluation | C13: scikit-learn | D13: Tool | E13: Confusion matrix, precision/recall, anomaly detection, evaluation | F13: https://scikit-learn.org/ | G13: Week 7
A14: Tool | B14: Dashboarding | C14: Power BI | D14: Tool | E14: AML MI: alerts, typologies, dispositions and false-positive rates | F14: https://www.microsoft.com/power-platform/products/power-bi | G14: Week 8
... A17: Cert | B17: Irish compliance body | C17: Compliance Institute (ACOI) | D17: Ireland | E17: Optional; the Irish professional body's local designations | F17: https://www.acoi.ie/ | G17: Week 8 / opt
